Workbook

Sheet 01_Master_Material
A1: 01_MASTER_MATERIAL | Warehouse Operations in a Heavy Equipment Manufacturing Environment
A3: Material Code | B3: Material Description | C3: Material Group | D3: Base UoM | E3: Purchase UoM | F3: Conversion Factor (Purchase to Base) | G3: Primary Supplier Code | H3: Standard Cost (per Base UoM) | I3: ABC Classification | J3: Criticality Flag | K3: Storage/Handling Class | L3: Min Stock Level | M3: Max Stock Level | N3: Lead Time (Days) | O3: Status
A4: MAT-00001 | B4: Hydraulic Cylinder Seal Kit 80mm | C4: Hydraulic Components | D4: PCS | E4: BOX | F4: 10 | G4: SUP-0012 | H4: 145.5 | I4: A | J4: Critical Spare | K4: Standard | L4: 20 | M4: 100 | N4: 14 | O4: Active
A5: MAT-00002 | B5: Steel Plate 10mm x 2m x 1m | C5: Raw Steel | D5: PCS | E5: PCS | F5: 1 | G5: SUP-0005 | H5: 320 | I5: A | J5: Standard | K5: Heavy/Bulk | L5: 10 | M5: 50 | N5: 21 | O5: Active
A6: MAT-00003 | B6: Engine Oil Filter (Cat 320D) | C6: Engine Parts | D6: PCS | E6: BOX | F6: 24 | G6: SUP-0021 | H6: 18.75 | I6: B | J6: Critical Spare | K6: Standard | L6: 50 | M6: 300 | N6: 7 | O6: Active
A7: MAT-00004 | B7: Hex Bolt M12x50 Grade 8.8 | C7: Fasteners | D7: PCS | E7: BOX | F7: 100 | G7: SUP-0009 | H7: 0.35 | I7: C | J7: Standard | K7: Standard | L7: 500 | M7: 5000 | N7: 10 | O7: Active
A8: MAT-00005 | B8: Industrial Degreaser 20L | C8: Consumables | D8: LTR | E8: BOX | F8: 20 | G8: SUP-0014 | H8: 4.2 | I8: C | J8: Standard | K8: Hazardous | L8: 40 | M8: 200 | N8: 5 | O8: Active
A9: MAT-00006 | B9: Track Roller Assembly (Komatsu D65) | C9: Hydraulic Components | D9: PCS | E9: PCS | F9: 1 | G9: SUP-0012 | H9: 890 | I9: A | J9: Critical Spare | K9: Heavy/Bulk | L9: 4 | M9: 20 | N9: 30 | O9: Active
A10: MAT-00007 | B10: Air Filter Element - Primary | C10: Engine Parts | D10: PCS | E10: BOX | F10: 12 | G10: SUP-0021 | H10: 32.1 | I10: B | J10: Standard | K10: Standard | L10: 30 | M10: 150 | N10: 10 | O10: Active
A11: MAT-00008 | B11: Hydraulic Hose 1/2in x 3m | C11: Hydraulic Components | D11: PCS | E11: PCS | F11: 1 | G11: SUP-0012 | H11: 54.9 | I11: B | J11: Critical Spare | K11: Standard | L11: 15 | M11: 80 | N11: 12 | O11: Active
A12: MAT-00009 | B12: Grease Cartridge NLGI2 400g | C12: Consumables | D12: PCS | E12: BOX | F12: 12 | G12: SUP-0014 | H12: 6.8 | I12: C | J12: Standard | K12: Standard | L12: 60 | M12: 400 | N12: 5 | O12: Active
A13: MAT-00010 | B13: Welding Electrode E7018 3.2mm | C13: Raw Steel | D13: KG | E13: BOX | F13: 5 | G13: SUP-0005 | H13: 3.95 | I13: C | J13: Standard | K13: Standard | L13: 100 | M13: 600 | N13: 7 | O13: Active
A14: MAT-00011 | B14: Final Drive Motor (Excavator PC200) | C14: Finished Spares | D14: PCS | E14: PCS | F14: 1 | G14: SUP-0033 | H14: 2450 | I14: A | J14: Critical Spare | K14: Heavy/Bulk | L14: 2 | M14: 10 | N14: 45 | O14: Active
A15: MAT-00012 | B15: Bucket Teeth (CAT style) | C15: Finished Spares | D15: PCS | E15: BOX | F15: 10 | G15: SUP-0033 | H15: 42 | I15: B | J15: Critical Spare | K15: Standard | L15: 25 | M15: 120 | N15: 20 | O15: Active
... A23: MAT-00020 | B23: Undercarriage Chain Link Assembly | C23: Finished Spares | D23: PCS | E23: PCS | F23: 1 | G23: SUP-0033 | H23: 1120 | I23: A | J23: Critical Spare | K23: Heavy/Bulk | L23: 2 | M23: 8 | N23: 40 | O23: Inactive
A26: Notes / Data Dictionary
A27: - Material Code: Primary key. Format MAT-##### used consistently across all worksheets.
A28: - ABC Classification: A = high value/usage, B = moderate, C = low value/high volume.
A29: - Criticality Flag: 'Critical Spare' = stockout risk causes production/machine downtime.
A30: - Conversion Factor: Multiply Purchase UoM quantity by this factor to obtain Base UoM quantity (used in PO reconciliation).
A31: - Status: Only 'Active' materials should be used in new transactions.

Sheet 02_Master_Supplier
A1: 02_MASTER_SUPPLIER | Warehouse Operations in a Heavy Equipment Manufacturing Environment
A3: Supplier Code | B3: Supplier Name | C3: Supplier Type | D3: Supplier Category | E3: Country | F3: Contact Person | G3: Contact Email | H3: Contact Phone | I3: Supplier Rating | J3: Status
A4: SUP-0005 | B4: PT Krakatau Steel Distribusi | C4: Authorized Distributor | D4: Local | E4: Indonesia | F4: Budi Santoso | G4: budi.santoso@krakatau-dist.co.id | H4: 021-5501234 | I4: Preferred | J4: Active
A5: SUP-0009 | B5: PT Fastener Nusantara | C5: Local Trader | D5: Local | E5: Indonesia | F5: Rina Wulandari | G5: rina@fastenernusantara.co.id | H5: 021-5502345 | I5: Approved | J5: Active
A6: SUP-0012 | B6: Komatsu Parts Indonesia | C6: Authorized Distributor | D6: Local | E6: Indonesia | F6: Agus Prasetyo | G6: agus.p@komatsuparts.co.id | H6: 021-5503456 | I6: Preferred | J6: Active
A7: SUP-0014 | B7: PT Kimia Pelumas Industri | C7: Local Trader | D7: Local | E7: Indonesia | F7: Siti Rahayu | G7: siti.rahayu@kpi-lube.co.id | H7: 021-5504567 | I7: Approved | J7: Active
A8: SUP-0021 | B8: Caterpillar Engine Parts Distributor | C8: Authorized Distributor | D8: Import | E8: Singapore | F8: Michael Tan | G8: michael.tan@catengine-sg.com | H8: +65-6511-2233 | I8: Preferred | J8: Active
A9: SUP-0033 | B9: Original Equipment Spares Corp | C9: Manufacturer | D9: Import | E9: Japan | F9: Kenji Watanabe | G9: k.watanabe@oescorp.jp | H9: +81-3-4455-6677 | I9: Preferred | J9: Active
A10: SUP-0002 | B10: PT Sumber Baja Perkasa | C10: Local Trader | D10: Local | E10: Indonesia | F10: Dedi Kurniawan | G10: dedi@sumberbaja.co.id | H10: 022-6601122 | I10: Under Review | J10: Active
A11: SUP-0018 | B11: Global Hydraulic Supply Pte Ltd | C11: Authorized Distributor | D11: Import | E11: Singapore | F11: Lisa Ong | G11: lisa.ong@ghsupply.sg | H11: +65-6522-3344 | I11: Approved | J11: Active
A12: SUP-0025 | B12: PT Mitra Konsumabel Industri | C12: Local Trader | D12: Local | E12: Indonesia | F12: Andi Firmansyah | G12: andi@mitrakonsumabel.co.id | H12: 021-5507890 | I12: Approved | J12: Active
A13: SUP-0040 | B13: Heavy Equipment Parts Trading Co. | C13: Local Trader | D13: Local | E13: Indonesia | F13: Yusuf Hidayat | G13: yusuf@heptrading.co.id | H13: 021-5508901 | I13: Under Review | J13: Inactive
A16: Notes / Data Dictionary
A17: - Supplier Code: Primary key. Must match Primary Supplier Code values used in 01_Master_Material.
A18: - Supplier Type: Manufacturer = direct OEM source; Authorized Distributor = official regional channel; Local Trader = non-exclusive reseller.
A19: - Supplier Rating: Purchasing-assigned reliability tier. 'Under Review' should not be used for new Critical Spare orders.
A20: - Assumption: Payment Terms, Tax ID, and Currency are out of scope (no Finance/AP worksheet exists).
A21: - Status: Only 'Active' suppliers should be selectable when creating a new Purchase Order.

Sheet 03_Master_Location
A1: 03_MASTER_LOCATION | Warehouse Operations in a Heavy Equipment Manufacturing Environment
A3: Location Code | B3: Location Description | C3: Zone | D3: Storage/Handling Requirement | E3: Pickable Flag | F3: Capacity (Max Qty) | G3: Status
A4: RCV-DOCK-01 | B4: Receiving Dock 1 | C4: Receiving | D4: Standard | E4: No | F4: 50 | G4: Active
A5: RCV-DOCK-02 | B5: Receiving Dock 2 (Heavy Cargo) | C5: Receiving | D5: Heavy/Bulk | E5: No | F5: 20 | G5: Active
A6: BLK-A-01 | B6: Bulk Storage Rack A-01 (Steel Plates) | C6: Storage | D6: Heavy/Bulk | E6: Yes | F6: 40 | G6: Active
A7: BLK-A-02 | B7: Bulk Storage Rack A-02 | C7: Storage | D7: Heavy/Bulk | E7: Yes | F7: 40 | G7: Active
A8: RCK-B-01-01 | B8: Standard Racking B-01 Level 1 | C8: Storage | D8: Standard | E8: Yes | F8: 200 | G8: Active
A9: RCK-B-01-02 | B9: Standard Racking B-01 Level 2 | C9: Storage | D9: Standard | E9: Yes | F9: 200 | G9: Active
A10: RCK-B-02-01 | B10: Standard Racking B-02 Level 1 | C10: Storage | D10: Standard | E10: Yes | F10: 200 | G10: Active
A11: HAZ-C-01 | B11: Hazardous Storage Cabinet C-01 | C11: Storage | D11: Hazardous | E11: Yes | F11: 60 | G11: Active
A12: QC-HOLD-01 | B12: Quarantine / QC Hold Area 1 | C12: Quarantine/QC Hold | D12: Standard | E12: No | F12: 30 | G12: Active
A13: SHP-STG-01 | B13: Shipping Staging Area 1 | C13: Shipping/Staging | D13: Standard | E13: No | F13: 50 | G13: Active
A14: RCK-B-03-01 | B14: Standard Racking B-03 Level 1 (Under Maintenance) | C14: Storage | D14: Standard | E14: No | F14: 200 | G14: Inactive
A17: Notes / Data Dictionary
A18: - Location Code: Primary key, format ZONE-RACK-LEVEL. Foreign key used in Put-Away, Stock Card, and Cycle Count.
A19: - Zone: Functional workflow stage. Only 'Storage' zone locations are expected to be Pickable = Yes.
A20: - Storage/Handling Requirement: Uses the same value list as Storage/Handling Class in 01_Master_Material.
A21: - Pickable Flag: Business rule enforced in 08_Picking_List.
A22: - Capacity (Max Qty): Denominator for the Dashboard's warehouse utilization KPI.
A23: - Design note: Current Utilization (%) is intentionally NOT stored here; it is calculated in 12_Dashboard from Stock Card data.

Sheet 04_Purchase_Order
A1: 04_PURCHASE_ORDER | Warehouse Operations in a Heavy Equipment Manufacturing Environment
A3: PO Number | B3: PO Line | C3: PO Date | D3: Supplier Code | E3: Supplier Name | F3: Material Code | G3: Material Description | H3: Purchase UoM | I3: Order Quantity | J3: Unit Price | K3: Line Total | L3: Conversion Factor (Ref) | M3: Standard Cost Equivalent | N3: Price Variance | O3: Price Variance % | P3: Order Priority | Q3: Lead Time (Days) Ref | R3: Expected Delivery Date | S3: PO Status | T3: Remarks
A4: PO-2026-0001 | B4: 10 | C4: 2026-06-01 | D4: SUP-0012 | E4: =INDEX('02_Master_Supplier'!$B:$B,MATCH(D4,'02_Master_Supplier'!$A:$A,0)) -> Komatsu Parts Indonesia | F4: MAT-00001 | G4: =INDEX('01_Master_Material'!$B:$B,MATCH(F4,'01_Master_Material'!$A:$A,0)) -> Hydraulic Cylinder Seal Kit 80mm | H4: =INDEX('01_Master_Material'!$E:$E,MATCH(F4,'01_Master_Material'!$A:$A,0)) -> BOX | I4: 5 | J4: 1500 | K4: =I4*J4 -> 7500 | L4: =INDEX('01_Master_Material'!$F:$F,MATCH(F4,'01_Master_Material'!$A:$A,0)) -> 10 | M4: =INDEX('01_Master_Material'!$H:$H,MATCH(F4,'01_Master_Material'!$A:$A,0))*L4 -> 1455 | N4: =J4-M4 -> 45 | O4: =IFERROR(N4/M4,0) -> 0.030927835 | P4: Standard | Q4: =INDEX('01_Master_Material'!$N:$N,MATCH(F4,'01_Master_Material'!$A:$A,0)) -> 14 | R4: =C4+Q4 -> 46188 | S4: Closed
A5: PO-2026-0001 | B5: 20 | C5: 2026-06-01 | D5: SUP-0012 | E5: =INDEX('02_Master_Supplier'!$B:$B,MATCH(D5,'02_Master_Supplier'!$A:$A,0)) -> Komatsu Parts Indonesia | F5: MAT-00008 | G5: =INDEX('01_Master_Material'!$B:$B,MATCH(F5,'01_Master_Material'!$A:$A,0)) -> Hydraulic Hose 1/2in x 3m | H5: =INDEX('01_Master_Material'!$E:$E,MATCH(F5,'01_Master_Material'!$A:$A,0)) -> PCS | I5: 30 | J5: 52 | K5: =I5*J5 -> 1560 | L5: =INDEX('01_Master_Material'!$F:$F,MATCH(F5,'01_Master_Material'!$A:$A,0)) -> 1 | M5: =INDEX('01_Master_Material'!$H:$H,MATCH(F5,'01_Master_Material'!$A:$A,0))*L5 -> 54.9 | N5: =J5-M5 -> -2.9 | O5: =IFERROR(N5/M5,0) -> -0.052823315 | P5: Standard | Q5: =INDEX('01_Master_Material'!$N:$N,MATCH(F5,'01_Master_Material'!$A:$A,0)) -> 12 | R5: =C5+Q5 -> 46186 | S5: Closed
A6: PO-2026-0002 | B6: 10 | C6: 2026-06-05 | D6: SUP-0021 | E6: =INDEX('02_Master_Supplier'!$B:$B,MATCH(D6,'02_Master_Supplier'!$A:$A,0)) -> Caterpillar Engine Parts Distributor | F6: MAT-00015 | G6: =INDEX('01_Master_Material'!$B:$B,MATCH(F6,'01_Master_Material'!$A:$A,0)) -> Turbocharger Assembly (Cat C15) | H6: =INDEX('01_Master_Material'!$E:$E,MATCH(F6,'01_Master_Material'!$A:$A,0)) -> PCS | I6: 2 | J6: 1450 | K6: =I6*J6 -> 2900 | L6: =INDEX('01_Master_Material'!$F:$F,MATCH(F6,'01_Master_Material'!$A:$A,0)) -> 1 | M6: =INDEX('01_Master_Material'!$H:$H,MATCH(F6,'01_Master_Material'!$A:$A,0))*L6 -> 1380 | N6: =J6-M6 -> 70 | O6: =IFERROR(N6/M6,0) -> 0.050724638 | P6: Urgent | Q6: =INDEX('01_Master_Material'!$N:$N,MATCH(F6,'01_Master_Material'!$A:$A,0)) -> 35 | R6: =C6+Q6 -> 46213 | S6: Open | T6: Emergency replacement - unit down
A7: PO-2026-0002 | B7: 20 | C7: 2026-06-05 | D7: SUP-0021 | E7: =INDEX('02_Master_Supplier'!$B:$B,MATCH(D7,'02_Master_Supplier'!$A:$A,0)) -> Caterpillar Engine Parts Distributor | F7: MAT-00003 | G7: =INDEX('01_Master_Material'!$B:$B,MATCH(F7,'01_Master_Material'!$A:$A,0)) -> Engine Oil Filter (Cat 320D) | H7: =INDEX('01_Master_Material'!$E:$E,MATCH(F7,'01_Master_Material'!$A:$A,0)) -> BOX | I7: 10 | J7: 430 | K7: =I7*J7 -> 4300 | L7: =INDEX('01_Master_Material'!$F:$F,MATCH(F7,'01_Master_Material'!$A:$A,0)) -> 24 | M7: =INDEX('01_Master_Material'!$H:$H,MATCH(F7,'01_Master_Material'!$A:$A,0))*L7 -> 450 | N7: =J7-M7 -> -20 | O7: =IFERROR(N7/M7,0) -> -0.044444444 | P7: Standard | Q7: =INDEX('01_Master_Material'!$N:$N,MATCH(F7,'01_Master_Material'!$A:$A,0)) -> 7 | R7: =C7+Q7 -> 46185 | S7: Partially Received
A8: PO-2026-0003 | B8: 10 | C8: 2026-06-10 | D8: SUP-0005 | E8: =INDEX('02_Master_Supplier'!$B:$B,MATCH(D8,'02_Master_Supplier'!$A:$A,0)) -> PT Krakatau Steel Distribusi | F8: MAT-00002 | G8: =INDEX('01_Master_Material'!$B:$B,MATCH(F8,'01_Master_Material'!$A:$A,0)) -> Steel Plate 10mm x 2m x 1m | H8: =INDEX('01_Master_Material'!$E:$E,MATCH(F8,'01_Master_Material'!$A:$A,0)) -> PCS | I8: 15 | J8: 315 | K8: =I8*J8 -> 4725 | L8: =INDEX('01_Master_Material'!$F:$F,MATCH(F8,'01_Master_Material'!$A:$A,0)) -> 1 | M8: =INDEX('01_Master_Material'!$H:$H,MATCH(F8,'01_Master_Material'!$A:$A,0))*L8 -> 320 | N8: =J8-M8 -> -5 | O8: =IFERROR(N8/M8,0) -> -0.015625 | P8: Standard | Q8: =INDEX('01_Master_Material'!$N:$N,MATCH(F8,'01_Master_Material'!$A:$A,0)) -> 21 | R8: =C8+Q8 -> 46204 | S8: Open
A9: PO-2026-0003 | B9: 20 | C9: 2026-06-10 | D9: SUP-0005 | E9: =INDEX('02_Master_Supplier'!$B:$B,MATCH(D9,'02_Master_Supplier'!$A:$A,0)) -> PT Krakatau Steel Distribusi | F9: MAT-00017 | G9: =INDEX('01_Master_Material'!$B:$B,MATCH(F9,'01_Master_Material'!$A:$A,0)) -> Steel I-Beam 6m Length | H9: =INDEX('01_Master_Material'!$E:$E,MATCH(F9,'01_Master_Material'!$A:$A,0)) -> PCS | I9: 8 | J9: 625 | K9: =I9*J9 -> 5000 | L9: =INDEX('01_Master_Material'!$F:$F,MATCH(F9,'01_Master_Material'!$A:$A,0)) -> 1 | M9: =INDEX('01_Master_Material'!$H:$H,MATCH(F9,'01_Master_Material'!$A:$A,0))*L9 -> 610 | N9: =J9-M9 -> 15 | O9: =IFERROR(N9/M9,0) -> 0.024590164 | P9: Standard | Q9: =INDEX('01_Master_Material'!$N:$N,MATCH(F9,'01_Master_Material'!$A:$A,0)) -> 25 | R9: =C9+Q9 -> 46208 | S9: Cancelled | T9: Project scope changed
A10: PO-2026-0004 | B10: 10 | C10: 2026-06-12 | D10: SUP-0033 | E10: =INDEX('02_Master_Supplier'!$B:$B,MATCH(D10,'02_Master_Supplier'!$A:$A,0)) -> Original Equipment Spares Corp | F10: MAT-00011 | G10: =INDEX('01_Master_Material'!$B:$B,MATCH(F10,'01_Master_Material'!$A:$A,0)) -> Final Drive Motor (Excavator PC200) | H10: =INDEX('01_Master_Material'!$E:$E,MATCH(F10,'01_Master_Material'!$A:$A,0)) -> PCS | I10: 1 | J10: 2500 | K10: =I10*J10 -> 2500 | L10: =INDEX('01_Master_Material'!$F:$F,MATCH(F10,'01_Master_Material'!$A:$A,0)) -> 1 | M10: =INDEX('01_Master_Material'!$H:$H,MATCH(F10,'01_Master_Material'!$A:$A,0))*L10 -> 2450 | N10: =J10-M10 -> 50 | O10: =IFERROR(N10/M10,0) -> 0.020408163 | P10: Urgent | Q10: =INDEX('01_Master_Material'!$N:$N,MATCH(F10,'01_Master_Material'!$A:$A,0)) -> 45 | R10: =C10+Q10 -> 46230 | S10: Open | T10: Critical spare - low stock
A11: PO-2026-0004 | B11: 20 | C11: 2026-06-12 | D11: SUP-0033 | E11: =INDEX('02_Master_Supplier'!$B:$B,MATCH(D11,'02_Master_Supplier'!$A:$A,0)) -> Original Equipment Spares Corp | F11: MAT-00020 | G11: =INDEX('01_Master_Material'!$B:$B,MATCH(F11,'01_Master_Material'!$A:$A,0)) -> Undercarriage Chain Link Assembly | H11: =INDEX('01_Master_Material'!$E:$E,MATCH(F11,'01_Master_Material'!$A:$A,0)) -> PCS | I11: 2 | J11: 1100 | K11: =I11*J11 -> 2200 | L11: =INDEX('01_Master_Material'!$F:$F,MATCH(F11,'01_Master_Material'!$A:$A,0)) -> 1 | M11: =INDEX('01_Master_Material'!$H:$H,MATCH(F11,'01_Master_Material'!$A:$A,0))*L11 -> 1120 | N11: =J11-M11 -> -20 | O11: =IFERROR(N11/M11,0) -> -0.017857143 | P11: Standard | Q11: =INDEX('01_Master_Material'!$N:$N,MATCH(F11,'01_Master_Material'!$A:$A,0)) -> 40 | R11: =C11+Q11 -> 46225 | S11: Open
A12: PO-2026-0005 | B12: 10 | C12: 2026-06-15 | D12: SUP-0009 | E12: =INDEX('02_Master_Supplier'!$B:$B,MATCH(D12,'02_Master_Supplier'!$A:$A,0)) -> PT Fastener Nusantara | F12: MAT-00004 | G12: =INDEX('01_Master_Material'!$B:$B,MATCH(F12,'01_Master_Material'!$A:$A,0)) -> Hex Bolt M12x50 Grade 8.8 | H12: =INDEX('01_Master_Material'!$E:$E,MATCH(F12,'01_Master_Material'!$A:$A,0)) -> BOX | I12: 50 | J12: 33.5 | K12: =I12*J12 -> 1675 | L12: =INDEX('01_Master_Material'!$F:$F,MATCH(F12,'01_Master_Material'!$A:$A,0)) -> 100 | M12: =INDEX('01_Master_Material'!$H:$H,MATCH(F12,'01_Master_Material'!$A:$A,0))*L12 -> 35 | N12: =J12-M12 -> -1.5 | O12: =IFERROR(N12/M12,0) -> -0.042857143 | P12: Standard | Q12: =INDEX('01_Master_Material'!$N:$N,MATCH(F12,'01_Master_Material'!$A:$A,0)) -> 10 | R12: =C12+Q12 -> 46198 | S12: Closed
A13: PO-2026-0005 | B13: 20 | C13: 2026-06-15 | D13: SUP-0009 | E13: =INDEX('02_Master_Supplier'!$B:$B,MATCH(D13,'02_Master_Supplier'!$A:$A,0)) -> PT Fastener Nusantara | F13: MAT-00014 | G13: =INDEX('01_Master_Material'!$B:$B,MATCH(F13,'01_Master_Material'!$A:$A,0)) -> Flat Washer M12 Zinc Plated | H13: =INDEX('01_Master_Material'!$E:$E,MATCH(F13,'01_Master_Material'!$A:$A,0)) -> BOX | I13: 40 | J13: 9.8 | K13: =I13*J13 -> 392 | L13: =INDEX('01_Master_Material'!$F:$F,MATCH(F13,'01_Master_Material'!$A:$A,0)) -> 200 | M13: =INDEX('01_Master_Material'!$H:$H,MATCH(F13,'01_Master_Material'!$A:$A,0))*L13 -> 10 | N13: =J13-M13 -> -0.2 | O13: =IFERROR(N13/M13,0) -> -0.02 | P13: Standard | Q13: =INDEX('01_Master_Material'!$N:$N,MATCH(F13,'01_Master_Material'!$A:$A,0)) -> 10 | R13: =C13+Q13 -> 46198 | S13: Closed
A16: Notes / Data Dictionary
A17: - PO Number + PO Line: Composite key. Foreign key referenced by 05_Goods_Receipt to validate received qty against ordered qty.
A18: - Supplier Name, Material Description, Purchase UoM, Conversion Factor, Lead Time: all pulled live via INDEX/MATCH from the master sheets (green font = cross-sheet link).
A19: - Standard Cost Equivalent = Material Standard Cost (per Base UoM) x Conversion Factor, converting it into Purchase UoM terms so it is directly comparable to the negotiated Unit Price.
A20: - Price Variance = Unit Price - Standard Cost Equivalent. Positive = paid above standard cost; Negative = paid below standard cost.
A21: - Expected Delivery Date = PO Date + Lead Time (Days) from Material Master. This is a formula, not a manually typed date.
A22: - PO Status is manually seeded for now (Open/Partially Received/Closed/Cancelled). Once 05_Goods_Receipt is built, this should become a formula comparing SUMIFS of received qty against Order Quantity.
A23: - Font color convention: blue = manual input, green = cross-sheet lookup formula, black = same-row calculated formula.
